{"duration":1618,"records":[{"duration":1067,"stepId":"org.kie.kogito.quarkus.common.deployment.KogitoAssetsProcessor#generateModel","started":"02:38:38.053","dependents":[256,338,265,266,281],"id":255,"thread":"build-25"},{"duration":244,"stepId":"org.kie.kogito.quarkus.common.deployment.KogitoAssetsProcessor#generateSources","started":"02:38:37.807","dependents":[254,255],"id":253,"thread":"build-45"},{"duration":111,"stepId":"io.quarkus.vertx.http.deployment.webjar.WebJarProcessor#processWebJarDevMode","started":"02:38:37.746","dependents":[250,252,339,251],"id":249,"thread":"build-40"},{"duration":78,"stepId":"io.quarkus.deployment.ide.IdeProcessor#detectRunningIdeProcesses","started":"02:38:37.742","dependents":[243],"id":242,"thread":"build-30"},{"duration":71,"stepId":"io.quarkus.deployment.steps.ConfigDescriptionBuildStep#createConfigDescriptions","started":"02:38:37.741","dependents":[334,241],"id":240,"thread":"build-25"},{"duration":60,"stepId":"io.quarkus.vertx.http.deployment.devmode.console.DevConsoleProcessor#collectTemplates","started":"02:38:37.742","dependents":[334],"id":237,"thread":"build-31"},{"duration":57,"stepId":"io.quarkus.deployment.steps.MainClassBuildStep#build","started":"02:38:39.290","dependents":[],"id":339,"thread":"build-29"},{"duration":53,"stepId":"io.quarkus.arc.deployment.ArcProcessor#generateResources","started":"02:38:39.189","dependents":[323,324,332,338,312,313,325,310,311,339,336,314],"id":309,"thread":"build-25"},{"duration":38,"stepId":"io.quarkus.deployment.steps.CompiledJavaVersionBuildStep#compiledJavaVersion","started":"02:38:37.747","dependents":[314],"id":223,"thread":"build-3"},{"duration":37,"stepId":"io.quarkus.resteasy.reactive.server.deployment.devconsole.ResteasyReactiveDevConsoleProcessor#collectStaticResourcesInfo","started":"02:38:37.767","dependents":[331],"id":238,"thread":"build-45"},{"duration":34,"stepId":"io.quarkus.deployment.steps.BannerProcessor#recordBanner","started":"02:38:37.747","dependents":[339,247],"id":196,"thread":"build-23"},{"duration":30,"stepId":"io.quarkus.deployment.dev.HotDeploymentWatchedFileBuildStep#setupWatchedFileHotDeployment","started":"02:38:37.766","dependents":[335,336],"id":233,"thread":"build-8"},{"duration":29,"stepId":"io.quarkus.vertx.http.deployment.devmode.tests.TestsProcessor#setupTestRoutes","started":"02:38:37.738","dependents":[334,326,330,339,173],"id":172,"thread":"build-5"},{"duration":28,"stepId":"org.kie.kogito.quarkus.common.deployment.KogitoAssetsProcessor#generateKogitoBuildContext","started":"02:38:37.779","dependents":[254,255,253],"id":239,"thread":"build-46"},{"duration":28,"stepId":"io.quarkus.vertx.http.deployment.devmode.ArcDevProcessor#eventsEndpoint","started":"02:38:37.741","dependents":[334,252,339],"id":183,"thread":"build-15"},{"duration":28,"stepId":"io.quarkus.vertx.http.deployment.devmode.console.DevConsoleProcessor#setupDeploymentSideHandling","started":"02:38:39.260","dependents":[335,336],"id":334,"thread":"build-29"},{"duration":28,"stepId":"io.quarkus.resteasy.reactive.server.deployment.ResteasyReactiveDevModeProcessor#addStaticResourcesExceptionMapper","started":"02:38:37.766","dependents":[339],"id":231,"thread":"build-26"},{"duration":27,"stepId":"io.quarkus.vertx.http.deployment.devmode.tests.TestsProcessor#toggleLiveReloadEnabled","started":"02:38:37.740","dependents":[334,252],"id":182,"thread":"build-16"},{"duration":25,"stepId":"io.quarkus.vertx.http.deployment.devmode.tests.TestsProcessor#toggleTestRunner","started":"02:38:37.741","dependents":[334,252],"id":164,"thread":"build-21"},{"duration":25,"stepId":"io.quarkus.vertx.http.deployment.devmode.tests.TestsProcessor#results","started":"02:38:37.741","dependents":[331],"id":168,"thread":"build-13"},{"duration":25,"stepId":"io.quarkus.vertx.http.deployment.devmode.tests.TestsProcessor#toggleInstrumentation","started":"02:38:37.741","dependents":[334,252],"id":165,"thread":"build-26"},{"duration":25,"stepId":"io.quarkus.arc.deployment.ArcProcessor#registerBeans","started":"02:38:39.144","dependents":[296,295,283,286,297,288,292,285,284,290,287,289,294],"id":282,"thread":"build-29"},{"duration":25,"stepId":"io.quarkus.vertx.core.deployment.VertxCoreProcessor#ioThreadDetector","started":"02:38:37.741","dependents":[339,171],"id":166,"thread":"build-1"},{"duration":23,"stepId":"io.quarkus.vertx.http.deployment.devmode.ArcDevProcessor#invocationsEndpoint","started":"02:38:37.747","dependents":[334,252,339],"id":186,"thread":"build-32"},{"duration":22,"stepId":"io.quarkus.vertx.http.deployment.VertxHttpProcessor#additionalBeans","started":"02:38:37.741","dependents":[266,278],"id":161,"thread":"build-24"},{"duration":22,"stepId":"io.quarkus.vertx.http.deployment.VertxHttpProcessor#filterMultipleVertxInstancesWarning","started":"02:38:37.745","dependents":[247,181],"id":178,"thread":"build-29"},{"duration":21,"stepId":"io.quarkus.vertx.core.deployment.VertxCoreProcessor#build_9d6b7122fb368970c50c3a870d1f672392cd8afb","started":"02:38:37.745","dependents":[338,185,281],"id":175,"thread":"build-35"},{"duration":21,"stepId":"io.quarkus.vertx.http.deployment.devmode.tests.TestsProcessor#toggleTestOutput","started":"02:38:37.745","dependents":[334,252],"id":180,"thread":"build-44"},{"duration":21,"stepId":"io.quarkus.vertx.core.deployment.VertxCoreProcessor#overrideContextInternalInterfaceToAddSafeGuards","started":"02:38:37.742","dependents":[323],"id":162,"thread":"build-8"},{"duration":21,"stepId":"io.quarkus.vertx.http.deployment.VertxHttpProcessor#bodyHandler","started":"02:38:37.747","dependents":[332,339],"id":184,"thread":"build-46"},{"duration":20,"stepId":"io.quarkus.deployment.logging.LoggingResourceProcessor#setProperty","started":"02:38:37.741","dependents":[339],"id":159,"thread":"build-10"},{"duration":20,"stepId":"io.quarkus.vertx.http.deployment.VertxHttpProcessor#hostDefault","started":"02:38:37.746","dependents":[176],"id":174,"thread":"build-39"},{"duration":20,"stepId":"io.quarkus.vertx.core.deployment.VertxCoreProcessor#createVertxThreadFactory","started":"02:38:37.752","dependents":[228,339],"id":187,"thread":"build-14"},{"duration":19,"stepId":"io.quarkus.deployment.dev.io.NioThreadPoolDevModeProcessor#setupTCCL","started":"02:38:37.741","dependents":[339],"id":158,"thread":"build-12"},{"duration":19,"stepId":"io.quarkus.smallrye.openapi.deployment.SmallRyeOpenApiProcessor#build","started":"02:38:39.144","dependents":[339,281],"id":280,"thread":"build-45"},{"duration":18,"stepId":"io.quarkus.vertx.http.deployment.HttpSecurityProcessor#initBasicAuth","started":"02:38:37.748","dependents":[295,292,339,279,290],"id":169,"thread":"build-49"},{"duration":18,"stepId":"io.quarkus.deployment.steps.ConfigGenerationBuildStep#watchConfigFiles","started":"02:38:37.747","dependents":[233],"id":163,"thread":"build-36"},{"duration":18,"stepId":"io.quarkus.vertx.http.deployment.devmode.tests.TestsProcessor#handleTestResult","started":"02:38:37.740","dependents":[334,252],"id":157,"thread":"build-6"},{"duration":18,"stepId":"io.quarkus.arc.deployment.BeanArchiveProcessor#build","started":"02:38:39.125","dependents":[271,275,312,296,269,274,325,322,278,314,268,267,273,270,294],"id":266,"thread":"build-8"},{"duration":18,"stepId":"io.quarkus.vertx.core.deployment.VertxCoreProcessor#eventLoopCount","started":"02:38:37.748","dependents":[337,339],"id":167,"thread":"build-45"},{"duration":17,"stepId":"io.quarkus.deployment.steps.ApplicationIndexBuildStep#build","started":"02:38:37.738","dependents":[170,285,155,314,278],"id":153,"thread":"build-28"},{"duration":17,"stepId":"io.quarkus.arc.deployment.SplitPackageProcessor#splitPackageDetection","started":"02:38:37.767","dependents":[309],"id":210,"thread":"build-49"},{"duration":15,"stepId":"io.quarkus.arc.deployment.ConfigBuildStep#additionalBeans","started":"02:38:37.752","dependents":[266,278],"id":179,"thread":"build-48"},{"duration":15,"stepId":"io.quarkus.vertx.core.deployment.VertxCoreProcessor#filterNettyHostsFileParsingWarn","started":"02:38:37.752","dependents":[247,181],"id":177,"thread":"build-34"},{"duration":15,"stepId":"io.quarkus.vertx.http.deployment.devmode.console.DevConsoleProcessor#handler","started":"02:38:37.736","dependents":[252,339,247],"id":140,"thread":"build-9"},{"duration":14,"stepId":"io.quarkus.deployment.ide.IdeProcessor#detectIdeFiles","started":"02:38:37.732","dependents":[243],"id":122,"thread":"build-2"},{"duration":14,"stepId":"io.quarkus.smallrye.health.deployment.SmallRyeHealthProcessor#build","started":"02:38:37.734","dependents":[266,149,339,278],"id":132,"thread":"build-4"},{"duration":14,"stepId":"io.quarkus.vertx.http.deployment.devmode.tests.TestsProcessor#runAllTests","started":"02:38:37.747","dependents":[334,252],"id":160,"thread":"build-38"},{"duration":14,"stepId":"io.quarkus.vertx.http.deployment.devmode.tests.TestsProcessor#printfailures","started":"02:38:37.740","dependents":[334,252],"id":152,"thread":"build-22"},{"duration":14,"stepId":"io.quarkus.vertx.http.deployment.devmode.tests.TestsProcessor#handleTestStatus","started":"02:38:37.740","dependents":[334,252],"id":148,"thread":"build-18"},{"duration":13,"stepId":"io.quarkus.deployment.steps.ThreadPoolSetup#createExecutor","started":"02:38:37.776","dependents":[332,232,229,230,234,339],"id":228,"thread":"build-32"},{"duration":12,"stepId":"io.quarkus.smallrye.context.deployment.SmallRyeContextPropagationProcessor#buildStatic","started":"02:38:37.742","dependents":[339],"id":151,"thread":"build-19"},{"duration":12,"stepId":"io.quarkus.arc.deployment.ArcProcessor#validate","started":"02:38:39.175","dependents":[323,307,300,304,308,301,302,303,309],"id":299,"thread":"build-45"},{"duration":11,"stepId":"io.quarkus.deployment.steps.CombinedIndexBuildStep#build","started":"02:38:37.766","dependents":[189,275,221,217,219,191,239,190,253,284,215,278,193,192,195,227,203,222,202,262,255,211,206,213,201,214,194,200,199,209,256,317,283,205,264,208,220,198,197,216,204,218,316],"id":188,"thread":"build-13"},{"duration":9,"stepId":"io.quarkus.resteasy.reactive.server.deployment.devconsole.ResteasyReactiveDevConsoleProcessor#exceptionMappers","started":"02:38:37.738","dependents":[335],"id":129,"thread":"build-14"},{"duration":9,"stepId":"io.quarkus.resteasy.reactive.server.deployment.devconsole.ResteasyReactiveDevConsoleProcessor#paramConverterProviders","started":"02:38:37.738","dependents":[335],"id":130,"thread":"build-20"},{"duration":8,"stepId":"io.quarkus.jackson.deployment.JacksonProcessor#supportMixins","started":"02:38:37.780","dependents":[338,295,292,339,290],"id":227,"thread":"build-29"},{"duration":8,"stepId":"io.quarkus.vertx.core.deployment.VertxCoreProcessor#build_9fb3ce360263cc99d07c9172ec2feeaa85afcc1a","started":"02:38:37.790","dependents":[295,292,336,290,332,236,337,313,330,339,235,335,291],"id":234,"thread":"build-35"},{"duration":8,"stepId":"io.quarkus.vertx.http.deployment.StaticResourcesProcessor#collectStaticResources","started":"02:38:39.120","dependents":[313],"id":265,"thread":"build-45"},{"duration":8,"stepId":"io.quarkus.deployment.index.ApplicationArchiveBuildStep#build","started":"02:38:37.758","dependents":[323,300,210,195,188,265,246,266,231,238],"id":170,"thread":"build-22"},{"duration":8,"stepId":"io.quarkus.arc.deployment.devconsole.ArcDevConsoleProcessor#collectBeanInfo","started":"02:38:39.188","dependents":[331],"id":308,"thread":"build-31"},{"duration":7,"stepId":"io.quarkus.resteasy.reactive.server.deployment.ResteasyReactiveProcessor#serverSerializers","started":"02:38:39.248","dependents":[338,325,339],"id":324,"thread":"build-29"},{"duration":7,"stepId":"io.quarkus.vertx.http.deployment.VertxHttpProcessor#cors","started":"02:38:37.748","dependents":[332,339],"id":154,"thread":"build-47"},{"duration":7,"stepId":"io.quarkus.deployment.logging.LoggingResourceProcessor#logConsoleCommand","started":"02:38:37.741","dependents":[319],"id":134,"thread":"build-11"},{"duration":6,"stepId":"io.quarkus.vertx.http.deployment.devmode.console.ConfigEditorProcessor#config","started":"02:38:37.811","dependents":[334,319,252,339,335],"id":241,"thread":"build-46"},{"duration":6,"stepId":"io.quarkus.deployment.steps.ConfigGenerationBuildStep#checkForBuildTimeConfigChange","started":"02:38:37.826","dependents":[339],"id":248,"thread":"build-46"},{"duration":6,"stepId":"io.quarkus.deployment.dev.testing.TestTracingProcessor#testConsoleCommand","started":"02:38:37.779","dependents":[319],"id":215,"thread":"build-16"},{"duration":6,"stepId":"io.quarkus.vertx.http.deployment.VertxHttpProcessor#logging","started":"02:38:37.747","dependents":[156],"id":150,"thread":"build-7"},{"duration":5,"stepId":"io.quarkus.smallrye.context.deployment.SmallRyeContextPropagationProcessor#build","started":"02:38:37.790","dependents":[295,292,339,290],"id":232,"thread":"build-29"},{"duration":4,"stepId":"io.quarkus.arc.deployment.devconsole.ArcDevConsoleProcessor#monitor","started":"02:38:37.750","dependents":[266,335,278],"id":149,"thread":"build-4"},{"duration":4,"stepId":"io.quarkus.resteasy.reactive.server.deployment.ResteasyReactiveProcessor#setupEndpoints","started":"02:38:39.242","dependents":[323,338,315,318,325,316,339,322],"id":314,"thread":"build-29"},{"duration":4,"stepId":"io.quarkus.deployment.logging.LoggingResourceProcessor#setupLoggingRuntimeInit","started":"02:38:37.822","dependents":[334,248,252,339],"id":247,"thread":"build-30"},{"duration":4,"stepId":"io.quarkus.swaggerui.deployment.SwaggerUiProcessor#getSwaggerUiFinalDestination","started":"02:38:37.738","dependents":[249],"id":97,"thread":"build-7"},{"duration":3,"stepId":"io.quarkus.deployment.steps.ClassTransformingBuildStep#handleClassTransformation","started":"02:38:39.248","dependents":[],"id":323,"thread":"build-46"},{"duration":3,"stepId":"io.quarkus.deployment.steps.NativeImageConfigBuildStep#build","started":"02:38:37.767","dependents":[339],"id":185,"thread":"build-1"},{"duration":3,"stepId":"io.quarkus.resteasy.reactive.server.deployment.ResteasyReactiveProcessor#setupDeployment","started":"02:38:39.256","dependents":[334,338,326,330,327,339],"id":325,"thread":"build-46"},{"duration":3,"stepId":"io.quarkus.arc.deployment.devconsole.ArcDevConsoleProcessor#exposeArcContainer","started":"02:38:37.738","dependents":[339,335],"id":98,"thread":"build-19"},{"duration":3,"stepId":"io.quarkus.resteasy.reactive.server.deployment.ResteasyReactiveScanningProcessor#handleCustomAnnotatedMethods","started":"02:38:39.121","dependents":[266,263,264,278],"id":262,"thread":"build-40"},{"duration":3,"stepId":"io.quarkus.vertx.http.deployment.devmode.console.DevConsoleProcessor#setupDevConsoleRoutes","started":"02:38:37.858","dependents":[334,326,330,339],"id":252,"thread":"build-30"},{"duration":3,"stepId":"io.quarkus.vertx.core.deployment.VertxCoreProcessor#createVertxContextHandlers","started":"02:38:37.732","dependents":[229,228,339],"id":19,"thread":"build-1"},{"duration":2,"stepId":"io.quarkus.vertx.http.deployment.devmode.console.DevConsoleProcessor#setupConsole","started":"02:38:37.738","dependents":[335,336],"id":62,"thread":"build-12"},{"duration":2,"stepId":"io.quarkus.smallrye.health.deployment.SmallRyeHealthProcessor#healthCheck","started":"02:38:37.736","dependents":[266,278],"id":34,"thread":"build-1"},{"duration":2,"stepId":"io.quarkus.vertx.http.deployment.VertxHttpProcessor#preinitializeRouter","started":"02:38:37.799","dependents":[295,330,292,339,290],"id":236,"thread":"build-8"},{"duration":2,"stepId":"io.quarkus.deployment.steps.MainClassBuildStep#applicationReflection","started":"02:38:37.743","dependents":[338],"id":108,"thread":"build-29"},{"duration":2,"stepId":"io.quarkus.deployment.logging.LoggingResourceProcessor#setupLoggingStaticInit","started":"02:38:37.732","dependents":[339],"id":17,"thread":"build-3"},{"duration":2,"stepId":"org.kie.kogito.quarkus.common.deployment.KogitoAssetsProcessor#runtimeConfigBuildStep","started":"02:38:37.782","dependents":[295,292,339,290],"id":209,"thread":"build-38"},{"duration":2,"stepId":"io.quarkus.mutiny.deployment.MutinyProcessor#runtimeInit","started":"02:38:37.790","dependents":[339],"id":229,"thread":"build-49"},{"duration":2,"stepId":"io.quarkus.deployment.steps.DevServicesConfigBuildStep#setup","started":"02:38:37.735","dependents":[38,97,241,335,336,226],"id":33,"thread":"build-10"},{"duration":2,"stepId":"io.quarkus.arc.deployment.SyntheticBeansProcessor#initRegular","started":"02:38:39.171","dependents":[297],"id":295,"thread":"build-25"},{"duration":2,"stepId":"io.quarkus.arc.deployment.ArcProcessor#setupExecutor","started":"02:38:37.790","dependents":[339],"id":230,"thread":"build-38"},{"duration":2,"stepId":"io.quarkus.netty.deployment.NettyProcessor#eagerlyInitClass","started":"02:38:37.735","dependents":[339],"id":36,"thread":"build-7"},{"duration":2,"stepId":"io.quarkus.deployment.logging.LoggingResourceProcessor#setUpDefaultLevels","started":"02:38:37.755","dependents":[247,226],"id":156,"thread":"build-4"},{"duration":2,"stepId":"io.quarkus.arc.deployment.staticmethods.InterceptedStaticMethodsProcessor#collectInterceptedStaticMethods","started":"02:38:39.171","dependents":[296,310,299],"id":294,"thread":"build-46"},{"duration":2,"stepId":"io.quarkus.smallrye.openapi.deployment.SmallRyeOpenApiProcessor#handler","started":"02:38:39.144","dependents":[334,328,326,295,330,329,292,339,290],"id":279,"thread":"build-46"},{"duration":2,"stepId":"io.quarkus.vertx.http.deployment.devmode.console.DevConsoleProcessor#buildTimeTemplates","started":"02:38:39.260","dependents":[335,336],"id":331,"thread":"build-46"},{"duration":2,"stepId":"io.quarkus.vertx.http.deployment.VertxHttpProcessor#initializeRouter","started":"02:38:39.260","dependents":[332,339],"id":330,"thread":"build-31"},{"duration":1,"stepId":"io.quarkus.vertx.http.deployment.devmode.ArcDevProcessor#registerRoutes","started":"02:38:39.188","dependents":[334,328,326,330,329,339,309],"id":307,"thread":"build-40"},{"duration":1,"stepId":"io.quarkus.smallrye.health.deployment.SmallRyeHealthProcessor#registerHealthUiHandler","started":"02:38:37.858","dependents":[334,326,330,339],"id":250,"thread":"build-46"},{"duration":1,"stepId":"io.quarkus.resteasy.reactive.server.deployment.devconsole.ResteasyReactiveDevConsoleProcessor#collectScores","started":"02:38:37.741","dependents":[335],"id":105,"thread":"build-27"},{"duration":1,"stepId":"io.quarkus.resteasy.reactive.server.deployment.ResteasyReactiveScanningProcessor#scanForFeatures","started":"02:38:37.785","dependents":[225,325],"id":221,"thread":"build-49"},{"duration":1,"stepId":"io.quarkus.arc.deployment.ArcProcessor#registerSyntheticObservers","started":"02:38:39.174","dependents":[338,298,299,309],"id":297,"thread":"build-45"},{"duration":1,"stepId":"io.quarkus.deployment.steps.DevModeBuildStep#watchChanges","started":"02:38:37.736","dependents":[233],"id":30,"thread":"build-15"},{"duration":1,"stepId":"io.quarkus.resteasy.reactive.common.deployment.ResteasyReactiveCommonProcessor#setupEndpoints","started":"02:38:39.242","dependents":[324,321,338,322],"id":312,"thread":"build-31"},{"duration":1,"stepId":"io.quarkus.vertx.http.deployment.VertxHttpProcessor#finalizeRouter","started":"02:38:39.262","dependents":[333,339,335,336],"id":332,"thread":"build-25"},{"duration":1,"stepId":"io.quarkus.jackson.deployment.JacksonProcessor#generateCustomizer","started":"02:38:37.784","dependents":[266],"id":213,"thread":"build-39"},{"duration":1,"stepId":"io.quarkus.swaggerui.deployment.SwaggerUiProcessor#registerSwaggerUiHandler","started":"02:38:37.858","dependents":[334,326,330,339],"id":251,"thread":"build-25"},{"duration":1,"stepId":"io.quarkus.deployment.steps.CapabilityAggregationStep#aggregateCapabilities","started":"02:38:37.752","dependents":[254,325,146,147,253,264,278,314,197,203,222,265,280,276],"id":145,"thread":"build-17"},{"duration":1,"stepId":"io.quarkus.deployment.steps.MainClassBuildStep#mainClassBuildStep","started":"02:38:37.780","dependents":[],"id":195,"thread":"build-48"},{"duration":1,"stepId":"io.quarkus.arc.deployment.CommandLineArgumentsProcessor#commandLineArgs","started":"02:38:37.741","dependents":[295,266,292,278,290],"id":102,"thread":"build-3"},{"duration":1,"stepId":"io.quarkus.smallrye.openapi.deployment.SmallRyeOpenApiProcessor#additionalBean","started":"02:38:37.750","dependents":[266,278],"id":144,"thread":"build-42"},{"duration":1,"stepId":"io.quarkus.arc.deployment.SyntheticBeansProcessor#initRuntime","started":"02:38:39.171","dependents":[293,297,339,335,336],"id":292,"thread":"build-45"},{"duration":1,"stepId":"io.quarkus.vertx.deployment.VertxProcessor#build","started":"02:38:39.171","dependents":[338,339,335,336],"id":291,"thread":"build-40"},{"duration":1,"stepId":"io.quarkus.vertx.http.deployment.StaticResourcesProcessor#runtimeInit","started":"02:38:39.242","dependents":[332,339],"id":313,"thread":"build-40"},{"duration":0,"stepId":"io.quarkus.resteasy.reactive.server.deployment.ResteasyReactiveProcessor#integrateEagerSecurity","started":"02:38:37.784","dependents":[314],"id":203,"thread":"build-5"},{"duration":0,"stepId":"io.quarkus.resteasy.reactive.common.deployment.ResteasyReactiveCommonProcessor#deprioritizeLegacyProviders","started":"02:38:37.738","dependents":[324],"id":53,"thread":"build-6"},{"duration":0,"stepId":"io.quarkus.vertx.http.deployment.devmode.console.DevConsoleProcessor#builder","started":"02:38:37.820","dependents":[334,252],"id":245,"thread":"build-30"},{"duration":0,"stepId":"io.quarkus.arc.deployment.BuildTimeEnabledProcessor#unlessBuildProperty","started":"02:38:37.779","dependents":[207,211,212],"id":191,"thread":"build-1"},{"duration":0,"stepId":"io.quarkus.vertx.deployment.VertxProcessor#registerVerticleClasses","started":"02:38:37.784","dependents":[338],"id":208,"thread":"build-12"},{"duration":0,"stepId":"io.quarkus.deployment.steps.ReflectiveHierarchyStep#ignoreJavaClassWarnings","started":"02:38:37.741","dependents":[316],"id":83,"thread":"build-29"},{"duration":0,"stepId":"io.quarkus.deployment.steps.ConfigGenerationBuildStep#suppressNonRuntimeConfigChanged","started":"02:38:37.740","dependents":[248],"id":64,"thread":"build-10"},{"duration":0,"stepId":"io.quarkus.resteasy.reactive.server.deployment.ResteasyReactiveDevModeProcessor#openCommand","started":"02:38:39.247","dependents":[319],"id":318,"thread":"build-31"},{"duration":0,"stepId":"io.quarkus.deployment.steps.ConfigGenerationBuildStep#staticInitSources","started":"02:38:37.742","dependents":[306],"id":88,"thread":"build-17"},{"duration":0,"stepId":"io.quarkus.deployment.steps.NativeImageResourcesStep#registerPackageResources","started":"02:38:37.734","dependents":[281],"id":11,"thread":"build-4"},{"duration":0,"stepId":"io.quarkus.smallrye.openapi.deployment.SmallRyeOpenApiProcessor#registerOpenApiSchemaClassesForReflection","started":"02:38:39.144","dependents":[338,316],"id":276,"thread":"build-45"},{"duration":0,"stepId":"io.quarkus.resteasy.reactive.jackson.deployment.processor.ResteasyReactiveJacksonProcessor#handleJsonAnnotations","started":"02:38:39.247","dependents":[320,338,339],"id":317,"thread":"build-29"},{"duration":0,"stepId":"io.quarkus.deployment.JniProcessor#setupJni","started":"02:38:37.738","dependents":[185],"id":49,"thread":"build-28"},{"duration":0,"stepId":"io.quarkus.resteasy.reactive.server.deployment.ResteasyReactiveCDIProcessor#additionalBeans","started":"02:38:37.786","dependents":[338,266,278],"id":225,"thread":"build-38"},{"duration":0,"stepId":"io.quarkus.deployment.steps.ConfigGenerationBuildStep#runtimeDefaultsConfig","started":"02:38:37.786","dependents":[281],"id":226,"thread":"build-49"},{"duration":0,"stepId":"io.quarkus.resteasy.reactive.server.deployment.ResteasyReactiveVertxWebSocketIntegrationProcessor#scanner","started":"02:38:37.741","dependents":[314],"id":69,"thread":"build-1"},{"duration":0,"stepId":"io.quarkus.resteasy.reactive.server.deployment.ResteasyReactiveScanningProcessor#defaultUnwrappedException","started":"02:38:37.732","dependents":[264],"id":7,"thread":"build-3"},{"duration":0,"stepId":"io.quarkus.netty.deployment.NettyProcessor#build","started":"02:38:37.746","dependents":[338,185],"id":119,"thread":"build-42"},{"duration":0,"stepId":"io.quarkus.arc.deployment.SyntheticBeansProcessor#initStatic","started":"02:38:39.171","dependents":[297,339],"id":290,"thread":"build-31"},{"duration":0,"stepId":"io.quarkus.deployment.console.ConsoleProcessor#setupConsole","started":"02:38:37.741","dependents":[246,244,173],"id":81,"thread":"build-29"},{"duration":0,"stepId":"io.quarkus.deployment.console.ConsoleProcessor#installCliCommands","started":"02:38:39.248","dependents":[335,336],"id":319,"thread":"build-29"},{"duration":0,"stepId":"io.quarkus.vertx.core.deployment.VertxCoreProcessor#cleanupVertxWarnings","started":"02:38:37.732","dependents":[247,181],"id":2,"thread":"build-2"},{"duration":0,"stepId":"io.quarkus.arc.deployment.UnremovableAnnotationsProcessor#unremovableBeans","started":"02:38:37.735","dependents":[299],"id":12,"thread":"build-6"},{"duration":0,"stepId":"io.quarkus.arc.deployment.ArcProcessor#loggerProducer","started":"02:38:37.742","dependents":[266,278],"id":93,"thread":"build-17"},{"duration":0,"stepId":"io.quarkus.resteasy.reactive.server.deployment.ResteasyReactiveProcessor#vertxIntegration","started":"02:38:37.746","dependents":[324,321,322],"id":118,"thread":"build-43"},{"duration":0,"stepId":"io.quarkus.arc.deployment.BuildTimeEnabledProcessor#buildExclusions","started":"02:38:37.784","dependents":[217],"id":207,"thread":"build-19"},{"duration":0,"stepId":"io.quarkus.arc.deployment.configproperties.ConfigPropertiesBuildStep#produceConfigPropertiesMetadata","started":"02:38:37.786","dependents":[222],"id":217,"thread":"build-10"},{"duration":0,"stepId":"org.kie.kogito.quarkus.common.deployment.KogitoCommonProcessor#kieWeaverServiceSPIResource","started":"02:38:37.745","dependents":[281],"id":115,"thread":"build-35"},{"duration":0,"stepId":"io.quarkus.resteasy.reactive.server.deployment.ResteasyReactiveCDIProcessor#contextInjection","started":"02:38:37.750","dependents":[272,273,266,278],"id":135,"thread":"build-4"},{"duration":0,"stepId":"io.quarkus.deployment.dev.IsolatedDevModeMain$5$1@4e408f34","started":"02:38:37.740","dependents":[314,278],"id":65,"thread":"build-8"},{"duration":0,"stepId":"io.quarkus.vertx.http.deployment.devmode.tests.TestsProcessor#runFailedTests","started":"02:38:37.735","dependents":[334,252],"id":15,"thread":"build-9"},{"duration":0,"stepId":"io.quarkus.deployment.steps.ConfigGenerationBuildStep#setupConfigOverride","started":"02:38:37.741","dependents":[],"id":76,"thread":"build-13"},{"duration":0,"stepId":"io.quarkus.smallrye.health.deployment.SmallRyeHealthProcessor#shutdownListener","started":"02:38:37.738","dependents":[333],"id":57,"thread":"build-26"},{"duration":0,"stepId":"io.quarkus.jackson.deployment.JacksonProcessor#register","started":"02:38:37.779","dependents":[338,266,316,278],"id":193,"thread":"build-34"},{"duration":0,"stepId":"io.quarkus.jsonp.deployment.JsonpProcessor#build","started":"02:38:37.741","dependents":[338,339],"id":87,"thread":"build-17"},{"duration":0,"stepId":"io.quarkus.resteasy.reactive.server.deployment.ResteasyReactiveScanningProcessor#scanForParamConverters_dcdfdd2a310a09abe5ee3f0ed2b2bc49f36f3d07","started":"02:38:37.786","dependents":[338,266,325,314,278],"id":224,"thread":"build-35"},{"duration":0,"stepId":"io.quarkus.resteasy.reactive.jackson.deployment.processor.ResteasyReactiveJacksonProcessor#exceptionMappers","started":"02:38:37.742","dependents":[264],"id":89,"thread":"build-23"},{"duration":0,"stepId":"io.quarkus.deployment.console.ConsoleProcessor#setupExceptionHandler","started":"02:38:37.820","dependents":[246],"id":244,"thread":"build-25"},{"duration":0,"stepId":"io.quarkus.deployment.steps.ProfileBuildStep#defaultProfile","started":"02:38:37.747","dependents":[226],"id":128,"thread":"build-23"},{"duration":0,"stepId":"io.quarkus.netty.deployment.NettyProcessor#registerQualifiers","started":"02:38:37.732","dependents":[266,278],"id":8,"thread":"build-4"},{"duration":0,"stepId":"io.quarkus.deployment.CollectionClassProcessor#setupCollectionClasses","started":"02:38:37.741","dependents":[338],"id":79,"thread":"build-23"},{"duration":0,"stepId":"io.quarkus.deployment.steps.NativeImageFeatureStep#generateNativeResourcesList","started":"02:38:39.164","dependents":[],"id":281,"thread":"build-46"},{"duration":0,"stepId":"io.quarkus.resteasy.reactive.server.deployment.ResteasyReactiveProcessor#handleClassLevelExceptionMappers","started":"02:38:39.121","dependents":[338,314],"id":258,"thread":"build-30"},{"duration":0,"stepId":"io.quarkus.deployment.steps.CurateOutcomeBuildStep#removeResources","started":"02:38:37.738","dependents":[323],"id":56,"thread":"build-3"},{"duration":0,"stepId":"io.quarkus.arc.deployment.ConfigBuildStep#validateConfigMappingsInjectionPoints","started":"02:38:39.188","dependents":[305,306],"id":301,"thread":"build-8"},{"duration":0,"stepId":"io.quarkus.arc.deployment.ConfigBuildStep#registerConfigMappingConverters","started":"02:38:37.779","dependents":[338],"id":192,"thread":"build-44"},{"duration":0,"stepId":"io.quarkus.arc.deployment.ConfigBuildStep#vetoMPConfigProperties","started":"02:38:37.752","dependents":[278],"id":141,"thread":"build-17"},{"duration":0,"stepId":"io.quarkus.smallrye.health.deployment.SmallRyeHealthProcessor#processSmallRyeHealthRuntimeConfig","started":"02:38:39.173","dependents":[339],"id":293,"thread":"build-40"},{"duration":0,"stepId":"org.kie.kogito.quarkus.common.deployment.KogitoCommonProcessor#kieWeaversSPIResource","started":"02:38:37.732","dependents":[281],"id":3,"thread":"build-4"},{"duration":0,"stepId":"io.quarkus.arc.deployment.TestsAsBeansProcessor#testAnnotations","started":"02:38:37.747","dependents":[266,149,278],"id":125,"thread":"build-27"},{"duration":0,"stepId":"io.quarkus.smallrye.context.deployment.SmallRyeContextPropagationProcessor#registerBean","started":"02:38:37.732","dependents":[266,278],"id":6,"thread":"build-2"},{"duration":0,"stepId":"io.quarkus.arc.deployment.ConfigBuildStep#registerConfigClasses","started":"02:38:39.188","dependents":[339],"id":305,"thread":"build-30"},{"duration":0,"stepId":"io.quarkus.arc.deployment.HotDeploymentConfigBuildStep#startup","started":"02:38:37.741","dependents":[72],"id":70,"thread":"build-17"},{"duration":0,"stepId":"io.quarkus.deployment.ide.IdeProcessor#effectiveIde","started":"02:38:37.820","dependents":[245,334,246,244],"id":243,"thread":"build-46"},{"duration":0,"stepId":"io.quarkus.deployment.steps.AdditionalClassLoaderResourcesBuildStep#appendAdditionalClassloaderResources","started":"02:38:37.746","dependents":[188],"id":120,"thread":"build-34"},{"duration":0,"stepId":"io.quarkus.deployment.steps.BootstrapConfigSetupBuildStep#setupBootstrapConfig","started":"02:38:37.745","dependents":[116,339],"id":112,"thread":"build-35"},{"duration":0,"stepId":"io.quarkus.resteasy.reactive.common.deployment.ResteasyReactiveCommonProcessor#resourceIndex","started":"02:38:39.120","dependents":[315,266,257],"id":256,"thread":"build-30"},{"duration":0,"stepId":"io.quarkus.arc.deployment.ReflectiveBeanClassesProcessor#implicitReflectiveBeanClasses","started":"02:38:39.171","dependents":[309],"id":286,"thread":"build-45"},{"duration":0,"stepId":"io.quarkus.arc.deployment.staticmethods.InterceptedStaticMethodsProcessor#callInitializer","started":"02:38:39.242","dependents":[339],"id":310,"thread":"build-30"},{"duration":0,"stepId":"io.quarkus.vertx.deployment.VertxProcessor#collectEventConsumers","started":"02:38:39.171","dependents":[297,291],"id":288,"thread":"build-25"},{"duration":0,"stepId":"org.kie.kogito.quarkus.decisions.deployment.DecisionsAssetsProcessor#stronglyTypeAdditionalClassesForReflection","started":"02:38:38.053","dependents":[338],"id":254,"thread":"build-30"},{"duration":0,"stepId":"io.quarkus.resteasy.reactive.server.deployment.ResteasyReactiveCDIProcessor#beanDefiningAnnotations","started":"02:38:37.750","dependents":[266,149,278],"id":136,"thread":"build-11"},{"duration":0,"stepId":"io.quarkus.smallrye.openapi.deployment.SmallRyeOpenApiProcessor#configFiles","started":"02:38:37.738","dependents":[233],"id":40,"thread":"build-22"},{"duration":0,"stepId":"io.quarkus.vertx.deployment.VertxProcessor#unremovableBeans","started":"02:38:37.741","dependents":[299],"id":86,"thread":"build-29"},{"duration":0,"stepId":"io.quarkus.netty.deployment.NettyProcessor#limitArenaSize","started":"02:38:37.747","dependents":[339],"id":126,"thread":"build-47"},{"duration":0,"stepId":"io.quarkus.arc.deployment.ArcProcessor#validateAsyncObserverExceptionHandlers","started":"02:38:39.188","dependents":[309],"id":302,"thread":"build-30"},{"duration":0,"stepId":"io.quarkus.vertx.http.deployment.HttpSecurityProcessor#builtins","started":"02:38:37.732","dependents":[266,147,278],"id":10,"thread":"build-4"},{"duration":0,"stepId":"io.quarkus.smallrye.health.deployment.SmallRyeHealthProcessor#defineHealthRoutes","started":"02:38:39.143","dependents":[334,326,330],"id":274,"thread":"build-46"},{"duration":0,"stepId":"io.quarkus.arc.deployment.configproperties.ConfigPropertiesBuildStep#setup","started":"02:38:37.786","dependents":[338,266,311,226],"id":222,"thread":"build-19"},{"duration":0,"stepId":"io.quarkus.deployment.index.ApplicationArchiveBuildStep#addConfiguredIndexedDependencies","started":"02:38:37.738","dependents":[170],"id":54,"thread":"build-17"},{"duration":0,"stepId":"io.quarkus.deployment.console.ConsoleProcessor#helpCommand","started":"02:38:37.741","dependents":[319],"id":85,"thread":"build-23"},{"duration":0,"stepId":"io.quarkus.arc.deployment.TestsAsBeansProcessor#testClassBeans","started":"02:38:37.741","dependents":[266,278],"id":84,"thread":"build-8"},{"duration":0,"stepId":"io.quarkus.resteasy.reactive.server.deployment.ResteasyReactiveProcessor#setMinimalNettyMaxOrderSize","started":"02:38:37.745","dependents":[126,119],"id":113,"thread":"build-41"},{"duration":0,"stepId":"io.quarkus.smallrye.openapi.deployment.SmallRyeOpenApiProcessor#smallryeOpenApiIndex","started":"02:38:39.143","dependents":[280,279,277,276],"id":275,"thread":"build-31"},{"duration":0,"stepId":"io.quarkus.arc.deployment.ArcProcessor#quarkusApplication","started":"02:38:37.784","dependents":[266,278],"id":204,"thread":"build-19"},{"duration":0,"stepId":"io.quarkus.vertx.http.deployment.devmode.console.DevConsoleProcessor#setupWebJar","started":"02:38:37.742","dependents":[249],"id":101,"thread":"build-23"},{"duration":0,"stepId":"io.quarkus.vertx.http.deployment.VertxHttpProcessor#httpRoot","started":"02:38:37.738","dependents":[332,62,328,318,280,58],"id":48,"thread":"build-27"},{"duration":0,"stepId":"io.quarkus.smallrye.openapi.deployment.SmallRyeOpenApiProcessor#addAutoFilters","started":"02:38:39.144","dependents":[280],"id":277,"thread":"build-29"},{"duration":0,"stepId":"io.quarkus.arc.deployment.ConfigBuildStep#registerConfigRootsAsBeans","started":"02:38:37.738","dependents":[295,292,290],"id":39,"thread":"build-24"},{"duration":0,"stepId":"io.quarkus.smallrye.context.deployment.SmallRyeContextPropagationProcessor#createSynthBeansForConfiguredInjectionPoints","started":"02:38:39.171","dependents":[295,292,339,290],"id":289,"thread":"build-8"},{"duration":0,"stepId":"io.quarkus.arc.deployment.ArcProcessor#marker","started":"02:38:37.741","dependents":[170],"id":68,"thread":"build-26"},{"duration":0,"stepId":"io.quarkus.resteasy.reactive.server.deployment.ResteasyReactiveProcessor#unremovableBeans","started":"02:38:39.121","dependents":[299],"id":261,"thread":"build-8"},{"duration":0,"stepId":"io.quarkus.deployment.ExtensionLoader#config","started":"02:38:37.732","dependents":[17,10,169,266,217,274,22,132,147,13,314,131,195,203,236,333,170,234,119,280,51,42,303,199,149,336,285,323,270,54,52,74,30,28,140,277,307,293,126,272,47,243,153,34,55,325,45,40,251,32,39,154,306,278,268,332,240,301,211,337,313,31,330,56,247,173,250,210,57,48,49,248,35,196,184,309,133,228,97,81,167,249,37,327,339,279],"id":9,"thread":"build-5"},{"duration":0,"stepId":"io.quarkus.arc.deployment.ArcProcessor#quarkusMain","started":"02:38:37.740","dependents":[266,149,278],"id":63,"thread":"build-1"},{"duration":0,"stepId":"io.quarkus.vertx.http.deployment.devmode.BuildMetricsDevConsoleProcessor#collectMetrics","started":"02:38:37.745","dependents":[331],"id":111,"thread":"build-17"},{"duration":0,"stepId":"io.quarkus.resteasy.reactive.jackson.deployment.processor.ResteasyReactiveJacksonProcessor#additionalProviders","started":"02:38:39.248","dependents":[324,321,322],"id":320,"thread":"build-46"},{"duration":0,"stepId":"io.quarkus.smallrye.context.deployment.SmallRyeContextPropagationProcessor#transformInjectionPoint","started":"02:38:37.747","dependents":[278],"id":123,"thread":"build-45"},{"duration":0,"stepId":"io.quarkus.deployment.steps.RegisterForReflectionBuildStep#build","started":"02:38:37.784","dependents":[338],"id":206,"thread":"build-35"},{"duration":0,"stepId":"io.quarkus.arc.deployment.AutoInjectFieldProcessor#autoInjectQualifiers","started":"02:38:39.143","dependents":[272,273],"id":267,"thread":"build-30"},{"duration":0,"stepId":"io.quarkus.vertx.deployment.VertxProcessor#autoAddScope","started":"02:38:37.742","dependents":[273],"id":99,"thread":"build-8"},{"duration":0,"stepId":"org.kie.kogito.quarkus.common.deployment.KogitoCommonProcessor#kieRuntimesSPIResource","started":"02:38:37.750","dependents":[281],"id":137,"thread":"build-37"},{"duration":0,"stepId":"org.kie.kogito.quarkus.decisions.deployment.DecisionsAssetsProcessor#featureBuildItem","started":"02:38:37.741","dependents":[339],"id":67,"thread":"build-26"},{"duration":0,"stepId":"io.quarkus.deployment.steps.BannerProcessor#watchBannerChanges","started":"02:38:37.738","dependents":[233],"id":52,"thread":"build-13"},{"duration":0,"stepId":"io.quarkus.resteasy.reactive.server.deployment.ResteasyReactiveProcessor#responseHeaderSupport","started":"02:38:37.735","dependents":[314],"id":20,"thread":"build-8"},{"duration":0,"stepId":"io.quarkus.arc.deployment.ArcProcessor#exposeCustomScopeNames","started":"02:38:37.742","dependents":[268,273,270,266,149,285,95,278],"id":92,"thread":"build-31"},{"duration":0,"stepId":"io.quarkus.resteasy.reactive.common.deployment.ResteasyReactiveCommonProcessor#scanResources","started":"02:38:39.120","dependents":[258,317,312,259,262,325,260,314,278,261],"id":257,"thread":"build-25"},{"duration":0,"stepId":"io.quarkus.deployment.logging.LoggingResourceProcessor#setUpDarkeningDefault","started":"02:38:37.741","dependents":[226],"id":73,"thread":"build-3"},{"duration":0,"stepId":"io.quarkus.deployment.steps.ReflectiveHierarchyStep#build","started":"02:38:39.247","dependents":[338],"id":316,"thread":"build-46"},{"duration":0,"stepId":"io.quarkus.deployment.steps.ShutdownListenerBuildStep#setupShutdown","started":"02:38:39.263","dependents":[339],"id":333,"thread":"build-46"},{"duration":0,"stepId":"io.quarkus.smallrye.openapi.deployment.SmallRyeOpenApiProcessor#contributeClassesToIndex","started":"02:38:37.732","dependents":[188],"id":5,"thread":"build-2"},{"duration":0,"stepId":"io.quarkus.vertx.deployment.EventBusCodecProcessor#registerCodecs","started":"02:38:39.143","dependents":[338,291],"id":269,"thread":"build-40"},{"duration":0,"stepId":"io.quarkus.arc.deployment.BuildTimeEnabledProcessor#ifBuildProfile","started":"02:38:37.783","dependents":[207,211,212],"id":201,"thread":"build-39"},{"duration":0,"stepId":"io.quarkus.resteasy.reactive.server.deployment.ResteasyReactiveProcessor#addAllWriteableMarker","started":"02:38:39.248","dependents":[323],"id":321,"thread":"build-31"},{"duration":0,"stepId":"io.quarkus.deployment.dev.testing.TestTracingProcessor#handle","started":"02:38:37.742","dependents":[247,181],"id":100,"thread":"build-8"},{"duration":0,"stepId":"io.quarkus.arc.deployment.WrongAnnotationUsageProcessor#detect","started":"02:38:39.171","dependents":[309],"id":285,"thread":"build-31"},{"duration":0,"stepId":"io.quarkus.resteasy.reactive.common.deployment.ResteasyReactiveCommonProcessor#buildResourceInterceptors","started":"02:38:39.124","dependents":[266,325,278],"id":263,"thread":"build-8"},{"duration":0,"stepId":"io.quarkus.deployment.dev.ConfigureDisableInstrumentationBuildStep#configure","started":"02:38:37.741","dependents":[335,336],"id":72,"thread":"build-1"},{"duration":0,"stepId":"io.quarkus.deployment.logging.LoggingWithPanacheProcessor#process","started":"02:38:37.779","dependents":[323],"id":190,"thread":"build-15"},{"duration":0,"stepId":"io.quarkus.arc.deployment.ConfigBuildStep#registerCustomConfigBeanTypes","started":"02:38:39.171","dependents":[338,295,292,290],"id":287,"thread":"build-40"},{"duration":0,"stepId":"io.quarkus.arc.deployment.BuildTimeEnabledProcessor#conditionTransformer","started":"02:38:37.785","dependents":[278],"id":212,"thread":"build-22"},{"duration":0,"stepId":"io.quarkus.vertx.http.deployment.HttpSecurityProcessor#setupAuthenticationMechanisms","started":"02:38:37.753","dependents":[332,266,339,309,279,278],"id":147,"thread":"build-42"},{"duration":0,"stepId":"io.quarkus.resteasy.reactive.server.deployment.ResteasyReactiveProcessor#recordableConstructor","started":"02:38:37.741","dependents":[339],"id":78,"thread":"build-17"},{"duration":0,"stepId":"io.quarkus.vertx.http.deployment.devmode.console.DevConsoleProcessor#config","started":"02:38:37.745","dependents":[331],"id":110,"thread":"build-41"},{"duration":0,"stepId":"io.quarkus.deployment.steps.CurateOutcomeBuildStep#curateOutcome","started":"02:38:37.738","dependents":[209,334,98,153,239,149,105,253,252,323,170,255,124,241,249,130,56,145,331,129],"id":51,"thread":"build-16"},{"duration":0,"stepId":"io.quarkus.resteasy.reactive.server.deployment.ResteasyReactiveProcessor#applyRuntimeConfig","started":"02:38:39.260","dependents":[339],"id":327,"thread":"build-30"},{"duration":0,"stepId":"io.quarkus.deployment.dev.testing.TestTracingProcessor#sharedStateListener","started":"02:38:37.752","dependents":[173],"id":143,"thread":"build-33"},{"duration":0,"stepId":"io.quarkus.vertx.http.deployment.devmode.console.DevConsoleProcessor#runtimeTemplates","started":"02:38:39.289","dependents":[339],"id":335,"thread":"build-46"},{"duration":0,"stepId":"io.quarkus.arc.deployment.ConfigBuildStep#registerConfigMappingsBean","started":"02:38:39.170","dependents":[297],"id":283,"thread":"build-46"},{"duration":0,"stepId":"io.quarkus.deployment.steps.ConfigGenerationBuildStep#extensionMappings","started":"02:38:37.783","dependents":[338,301,283,303,284],"id":199,"thread":"build-24"},{"duration":0,"stepId":"io.quarkus.arc.deployment.ConfigBuildStep#validateConfigInjectionPoints","started":"02:38:39.188","dependents":[311],"id":304,"thread":"build-46"},{"duration":0,"stepId":"io.quarkus.deployment.logging.LoggingResourceProcessor#registerMetrics","started":"02:38:37.738","dependents":[339,247],"id":55,"thread":"build-8"},{"duration":0,"stepId":"io.quarkus.vertx.core.deployment.VertxCoreProcessor#preventLoggerContention","started":"02:38:37.738","dependents":[156],"id":43,"thread":"build-14"},{"duration":0,"stepId":"io.quarkus.deployment.ForkJoinPoolProcessor#setProperty","started":"02:38:37.742","dependents":[339],"id":104,"thread":"build-17"},{"duration":0,"stepId":"io.quarkus.smallrye.openapi.deployment.SmallRyeOpenApiProcessor#classLoaderHack","started":"02:38:37.737","dependents":[339],"id":31,"thread":"build-15"},{"duration":0,"stepId":"io.quarkus.arc.deployment.StartupBuildSteps#registerStartupObservers","started":"02:38:39.175","dependents":[299],"id":298,"thread":"build-40"},{"duration":0,"stepId":"org.kie.kogito.quarkus.common.deployment.KogitoCommonProcessor#kieWeaversImplReflectiveClass","started":"02:38:37.745","dependents":[338],"id":114,"thread":"build-42"},{"duration":0,"stepId":"io.quarkus.resteasy.reactive.server.deployment.ResteasyReactiveScanningProcessor#compressionSupport","started":"02:38:37.738","dependents":[314],"id":47,"thread":"build-12"},{"duration":0,"stepId":"io.quarkus.resteasy.reactive.server.deployment.ResteasyReactiveProcessor#generateCustomProducer","started":"02:38:39.121","dependents":[266,278],"id":259,"thread":"build-46"},{"duration":0,"stepId":"io.quarkus.deployment.pkg.steps.JarResultBuildStep#outputTarget","started":"02:38:37.738","dependents":[209,255,280,239,41,40,253],"id":37,"thread":"build-10"},{"duration":0,"stepId":"io.quarkus.netty.deployment.NettyProcessor#setNettyMachineId","started":"02:38:37.740","dependents":[339],"id":66,"thread":"build-17"},{"duration":0,"stepId":"io.quarkus.resteasy.reactive.jackson.deployment.processor.ResteasyReactiveJacksonProcessor#customExceptionMappers","started":"02:38:37.746","dependents":[262],"id":121,"thread":"build-33"},{"duration":0,"stepId":"io.quarkus.arc.deployment.ArcProcessor#launchMode","started":"02:38:37.731","dependents":[266,278],"id":1,"thread":"build-1"},{"duration":0,"stepId":"io.quarkus.resteasy.reactive.server.deployment.ResteasyReactiveScanningProcessor#asyncSupport","started":"02:38:37.742","dependents":[314],"id":103,"thread":"build-7"},{"duration":0,"stepId":"io.quarkus.arc.deployment.ObserverValidationProcessor#validateApplicationObserver","started":"02:38:39.188","dependents":[309],"id":300,"thread":"build-25"},{"duration":0,"stepId":"io.quarkus.arc.deployment.ConfigBuildStep#validateConfigPropertiesInjectionPoints","started":"02:38:39.188","dependents":[305],"id":303,"thread":"build-29"},{"duration":0,"stepId":"io.quarkus.resteasy.reactive.server.deployment.ResteasyReactiveScanningProcessor#scanForContextResolvers","started":"02:38:37.785","dependents":[338,266,325,278],"id":220,"thread":"build-12"},{"duration":0,"stepId":"org.kie.kogito.quarkus.decisions.deployment.DecisionsAssetsProcessor#reflectiveDMNREST","started":"02:38:37.742","dependents":[316],"id":96,"thread":"build-8"},{"duration":0,"stepId":"io.quarkus.arc.deployment.ArcProcessor#transformListAllInjectionPoints","started":"02:38:37.735","dependents":[278],"id":14,"thread":"build-11"},{"duration":0,"stepId":"io.quarkus.vertx.deployment.VertxProcessor#featureAndCapability","started":"02:38:37.752","dependents":[145,339],"id":142,"thread":"build-2"},{"duration":0,"stepId":"io.quarkus.resteasy.reactive.server.deployment.ResteasyReactiveProcessor#responseStatusSupport","started":"02:38:37.741","dependents":[314],"id":71,"thread":"build-8"},{"duration":0,"stepId":"io.quarkus.resteasy.reactive.jackson.deployment.processor.ResteasyReactiveJacksonProcessor#jsonDefault","started":"02:38:37.735","dependents":[314],"id":18,"thread":"build-10"},{"duration":0,"stepId":"io.quarkus.resteasy.reactive.server.deployment.ResteasyReactiveScanningProcessor#scanForParamConverters_59e3169e3a646b7fcf3083416f558434b73816c5","started":"02:38:37.785","dependents":[224],"id":219,"thread":"build-38"},{"duration":0,"stepId":"io.quarkus.resteasy.reactive.server.deployment.ResteasyReactiveProcessor#additionalAsyncTypeMethodScanners","started":"02:38:37.742","dependents":[314],"id":91,"thread":"build-23"},{"duration":0,"stepId":"io.quarkus.deployment.logging.LoggingResourceProcessor#setupStackTraceFormatter","started":"02:38:37.821","dependents":[247],"id":246,"thread":"build-46"},{"duration":0,"stepId":"org.kie.kogito.quarkus.decisions.deployment.DecisionsAssetsProcessor#dmnRuntimeServiceReflectiveClass","started":"02:38:37.732","dependents":[338],"id":4,"thread":"build-3"},{"duration":0,"stepId":"io.quarkus.arc.deployment.HotDeploymentConfigBuildStep#configFile","started":"02:38:37.735","dependents":[233],"id":21,"thread":"build-8"},{"duration":0,"stepId":"io.quarkus.arc.deployment.BuildTimeEnabledProcessor#unlessBuildProfile","started":"02:38:37.779","dependents":[207,211,212],"id":189,"thread":"build-14"},{"duration":0,"stepId":"io.quarkus.deployment.pkg.steps.PackageTypeVerificationBuildStep#verify","started":"02:38:37.741","dependents":[335,336],"id":74,"thread":"build-23"},{"duration":0,"stepId":"io.quarkus.deployment.console.ConsoleProcessor#quitCommand","started":"02:38:37.735","dependents":[319],"id":25,"thread":"build-11"},{"duration":0,"stepId":"io.quarkus.arc.deployment.ConfigBuildStep#validateConfigValues","started":"02:38:39.242","dependents":[338,339],"id":311,"thread":"build-46"},{"duration":0,"stepId":"io.quarkus.resteasy.reactive.server.deployment.ResteasyReactiveDevModeProcessor#addReactiveRoutesExceptionMapper","started":"02:38:37.735","dependents":[339],"id":23,"thread":"build-9"},{"duration":0,"stepId":"io.quarkus.deployment.steps.ConfigGenerationBuildStep#generateConfigClass","started":"02:38:39.188","dependents":[338],"id":306,"thread":"build-25"},{"duration":0,"stepId":"io.quarkus.deployment.logging.LoggingResourceProcessor#setupLogFilters","started":"02:38:37.740","dependents":[247,181],"id":61,"thread":"build-13"},{"duration":0,"stepId":"io.quarkus.arc.deployment.AutoProducerMethodsProcessor#annotationTransformer","started":"02:38:39.143","dependents":[278],"id":268,"thread":"build-25"},{"duration":0,"stepId":"io.quarkus.deployment.recording.substitutions.AdditionalSubstitutionsBuildStep#additionalSubstitutions","started":"02:38:37.740","dependents":[339],"id":60,"thread":"build-3"},{"duration":0,"stepId":"io.quarkus.vertx.http.deployment.VertxHttpProcessor#notFoundRoutes","started":"02:38:39.260","dependents":[328,329],"id":326,"thread":"build-40"},{"duration":0,"stepId":"io.quarkus.vertx.http.deployment.HttpSecurityProcessor#initMtlsClientAuth","started":"02:38:37.748","dependents":[295,292,339,290],"id":133,"thread":"build-27"},{"duration":0,"stepId":"io.quarkus.deployment.steps.RuntimeConfigSetupBuildStep#setupRuntimeConfig","started":"02:38:37.745","dependents":[250,293,248,169,196,184,336,251,154,133,131,332,236,333,228,337,234,313,330,167,327,339,279,247],"id":116,"thread":"build-17"},{"duration":0,"stepId":"io.quarkus.deployment.SslProcessor#setupNativeSsl","started":"02:38:37.735","dependents":[185],"id":13,"thread":"build-15"},{"duration":0,"stepId":"io.quarkus.deployment.steps.CapabilityAggregationStep#provideCapabilities","started":"02:38:37.747","dependents":[145],"id":124,"thread":"build-37"},{"duration":0,"stepId":"io.quarkus.resteasy.reactive.server.deployment.ResteasyReactiveScanningProcessor#scanForDynamicFeatures","started":"02:38:37.785","dependents":[225,325],"id":218,"thread":"build-35"},{"duration":0,"stepId":"io.quarkus.resteasy.reactive.server.deployment.ResteasyReactiveProcessor#additionalReflection","started":"02:38:39.248","dependents":[338],"id":322,"thread":"build-40"},{"duration":0,"stepId":"io.quarkus.vertx.http.deployment.VertxHttpProcessor#frameworkRoot","started":"02:38:37.738","dependents":[250,307,62,172,334,318,274,252,251,332,97,42,330,279],"id":35,"thread":"build-15"},{"duration":0,"stepId":"io.quarkus.netty.deployment.NettyProcessor#cleanup","started":"02:38:37.747","dependents":[247,181],"id":127,"thread":"build-46"},{"duration":0,"stepId":"io.quarkus.resteasy.reactive.jackson.deployment.processor.ResteasyReactiveJacksonProcessor#handleFieldSecurity","started":"02:38:39.247","dependents":[317],"id":315,"thread":"build-40"},{"duration":0,"stepId":"io.quarkus.deployment.steps.ConfigBuildSteps#generateConfigSources","started":"02:38:37.767","dependents":[],"id":176,"thread":"build-5"},{"duration":0,"stepId":"io.quarkus.arc.deployment.BuildTimeEnabledProcessor#ifBuildProperty","started":"02:38:37.784","dependents":[207,211,212],"id":205,"thread":"build-10"},{"duration":0,"stepId":"org.kie.kogito.quarkus.common.deployment.KogitoCommonProcessor#kieRuntimesImplReflectiveClass","started":"02:38:37.742","dependents":[338],"id":106,"thread":"build-7"},{"duration":0,"stepId":"io.quarkus.arc.deployment.ArcProcessor#feature","started":"02:38:37.741","dependents":[339],"id":80,"thread":"build-13"},{"duration":0,"stepId":"io.quarkus.vertx.http.deployment.devmode.tests.TestsProcessor#forceRestart","started":"02:38:37.735","dependents":[334,252],"id":26,"thread":"build-15"},{"duration":0,"stepId":"io.quarkus.deployment.recording.AnnotationProxyBuildStep#build","started":"02:38:37.756","dependents":[291],"id":155,"thread":"build-19"},{"duration":0,"stepId":"io.quarkus.vertx.core.deployment.VertxCoreProcessor#registerVerticleClasses","started":"02:38:37.782","dependents":[338],"id":198,"thread":"build-4"},{"duration":0,"stepId":"io.quarkus.arc.deployment.ArcProcessor#unremovableAsyncObserverExceptionHandlers","started":"02:38:37.738","dependents":[299],"id":44,"thread":"build-3"},{"duration":0,"stepId":"io.quarkus.arc.deployment.LookupConditionsProcessor#suppressConditionsGenerators","started":"02:38:39.143","dependents":[278],"id":271,"thread":"build-45"},{"duration":0,"stepId":"io.quarkus.jackson.deployment.JacksonProcessor#autoRegisterModules","started":"02:38:37.784","dependents":[213],"id":202,"thread":"build-22"},{"duration":0,"stepId":"io.quarkus.swaggerui.deployment.SwaggerUiProcessor#brandingFiles","started":"02:38:37.741","dependents":[233],"id":75,"thread":"build-1"},{"duration":0,"stepId":"io.quarkus.resteasy.reactive.server.deployment.ResteasyReactiveScanningProcessor#scanForExceptionMappers","started":"02:38:39.124","dependents":[338,266,325,278],"id":264,"thread":"build-31"},{"duration":0,"stepId":"io.quarkus.smallrye.health.deployment.SmallRyeHealthProcessor#registerUiExtension","started":"02:38:37.738","dependents":[249],"id":42,"thread":"build-1"},{"duration":0,"stepId":"io.quarkus.deployment.pkg.steps.FileSystemResourcesBuildStep#notNormalMode","started":"02:38:37.738","dependents":[],"id":41,"thread":"build-15"},{"duration":0,"stepId":"io.quarkus.vertx.http.deployment.devmode.console.ConfigEditorProcessor#handleRequests","started":"02:38:37.738","dependents":[334,252],"id":38,"thread":"build-22"},{"duration":0,"stepId":"io.quarkus.smallrye.health.deployment.SmallRyeHealthProcessor#brandingFiles","started":"02:38:37.738","dependents":[233],"id":45,"thread":"build-20"},{"duration":0,"stepId":"io.quarkus.resteasy.reactive.jackson.deployment.processor.ResteasyReactiveJacksonProcessor#beans","started":"02:38:37.738","dependents":[266,278],"id":46,"thread":"build-18"},{"duration":0,"stepId":"io.quarkus.resteasy.reactive.server.deployment.ResteasyReactiveProcessor#securityExceptionMappers","started":"02:38:37.745","dependents":[264],"id":109,"thread":"build-35"},{"duration":0,"stepId":"io.quarkus.arc.deployment.StartupBuildSteps#addScope","started":"02:38:37.742","dependents":[273],"id":95,"thread":"build-23"},{"duration":0,"stepId":"io.quarkus.deployment.logging.LoggingResourceProcessor#setUpDefaultLogCleanupFilters","started":"02:38:37.767","dependents":[226],"id":181,"thread":"build-34"},{"duration":0,"stepId":"io.quarkus.mutiny.deployment.MutinyProcessor#buildTimeInit","started":"02:38:37.735","dependents":[339],"id":27,"thread":"build-1"},{"duration":0,"stepId":"io.quarkus.resteasy.reactive.server.deployment.ResteasyReactiveProcessor#buildSetup","started":"02:38:37.735","dependents":[339],"id":24,"thread":"build-13"},{"duration":0,"stepId":"io.quarkus.smallrye.health.deployment.SmallRyeHealthProcessor#annotationTransformer","started":"02:38:39.143","dependents":[278],"id":270,"thread":"build-29"},{"duration":0,"stepId":"io.quarkus.arc.deployment.LifecycleEventsBuildStep#startupEvent","started":"02:38:39.289","dependents":[337,339],"id":336,"thread":"build-25"},{"duration":0,"stepId":"io.quarkus.arc.deployment.AutoAddScopeProcessor#annotationTransformer","started":"02:38:39.144","dependents":[299,278],"id":273,"thread":"build-29"},{"duration":0,"stepId":"org.kie.kogito.quarkus.common.deployment.KogitoCommonProcessor#kieRuntimeServiceSPIResource","started":"02:38:37.745","dependents":[281],"id":107,"thread":"build-17"},{"duration":0,"stepId":"io.quarkus.jackson.deployment.JacksonProcessor#unremovable","started":"02:38:37.782","dependents":[299],"id":197,"thread":"build-6"},{"duration":0,"stepId":"io.quarkus.resteasy.reactive.server.deployment.ResteasyReactiveDevModeProcessor#addAdditionalEndpointsExceptionMapper","started":"02:38:39.260","dependents":[339],"id":328,"thread":"build-46"},{"duration":0,"stepId":"io.quarkus.smallrye.openapi.deployment.SmallRyeOpenApiProcessor#logCleanup","started":"02:38:37.740","dependents":[247,181],"id":59,"thread":"build-3"},{"duration":0,"stepId":"io.quarkus.deployment.ConstructorPropertiesProcessor#build","started":"02:38:37.780","dependents":[338],"id":194,"thread":"build-21"},{"duration":0,"stepId":"io.quarkus.vertx.http.deployment.HttpSecurityProcessor#initFormAuth","started":"02:38:37.748","dependents":[334,326,295,330,292,339,290],"id":131,"thread":"build-37"},{"duration":0,"stepId":"io.quarkus.deployment.dev.testing.TestTracingProcessor#startTesting","started":"02:38:37.767","dependents":[335,336,247],"id":173,"thread":"build-22"},{"duration":0,"stepId":"io.quarkus.arc.deployment.StartupBuildSteps#unremovableBeans","started":"02:38:37.741","dependents":[299],"id":77,"thread":"build-3"},{"duration":0,"stepId":"io.quarkus.arc.deployment.ConfigBuildStep#registerConfigPropertiesBean","started":"02:38:39.171","dependents":[297],"id":284,"thread":"build-30"},{"duration":0,"stepId":"io.quarkus.resteasy.reactive.server.deployment.ResteasyReactiveCDIProcessor#pathInterfaceImpls","started":"02:38:39.121","dependents":[266,278],"id":260,"thread":"build-31"},{"duration":0,"stepId":"io.quarkus.resteasy.reactive.common.deployment.ResteasyReactiveCommonProcessor#handleApplication","started":"02:38:37.784","dependents":[221,312,219,325,263,264,220,314,324,216,338,218,214],"id":211,"thread":"build-5"},{"duration":0,"stepId":"io.quarkus.arc.deployment.ConfigBuildStep#generateConfigClasses","started":"02:38:37.783","dependents":[338,301,283,303,284],"id":200,"thread":"build-36"},{"duration":0,"stepId":"io.quarkus.arc.deployment.staticmethods.InterceptedStaticMethodsProcessor#processInterceptedStaticMethods","started":"02:38:39.174","dependents":[323,338],"id":296,"thread":"build-40"},{"duration":0,"stepId":"io.quarkus.resteasy.reactive.server.deployment.ResteasyReactiveScanningProcessor#scanForInterceptors","started":"02:38:37.785","dependents":[263],"id":216,"thread":"build-19"},{"duration":0,"stepId":"io.quarkus.resteasy.reactive.server.deployment.devconsole.ResteasyReactiveDevConsoleProcessor#collectAdditionalEndpoints","started":"02:38:39.260","dependents":[331],"id":329,"thread":"build-25"},{"duration":0,"stepId":"org.kie.kogito.quarkus.common.deployment.KogitoInternalObjectMapperProvider#objectMapperSPI","started":"02:38:37.742","dependents":[281],"id":94,"thread":"build-31"},{"duration":0,"stepId":"io.quarkus.vertx.http.deployment.VertxHttpProcessor#openSocket","started":"02:38:39.290","dependents":[338,339],"id":337,"thread":"build-46"},{"duration":0,"stepId":"io.quarkus.arc.deployment.AutoInjectFieldProcessor#annotationTransformer","started":"02:38:39.144","dependents":[278],"id":272,"thread":"build-25"},{"duration":0,"stepId":"io.quarkus.resteasy.reactive.server.deployment.ResteasyReactiveScanningProcessor#cacheControlSupport","started":"02:38:37.745","dependents":[314],"id":117,"thread":"build-42"},{"duration":0,"stepId":"io.quarkus.arc.deployment.ArcProcessor#initialize","started":"02:38:39.144","dependents":[308,282],"id":278,"thread":"build-25"},{"duration":0,"stepId":"io.quarkus.deployment.steps.ApplicationInfoBuildStep#create","started":"02:38:37.737","dependents":[339],"id":32,"thread":"build-22"},{"duration":0,"stepId":"io.quarkus.vertx.deployment.VertxProcessor#registerBean","started":"02:38:37.741","dependents":[266,278],"id":82,"thread":"build-8"},{"duration":0,"stepId":"io.quarkus.deployment.ExtensionLoader#booleanSupplierFactory","started":"02:38:37.741","dependents":[124],"id":90,"thread":"build-29"},{"duration":0,"stepId":"io.quarkus.smallrye.health.deployment.SmallRyeHealthProcessor#processSmallRyeHealthConfigValues","started":"02:38:37.736","dependents":[339],"id":28,"thread":"build-11"},{"duration":0,"stepId":"io.quarkus.netty.deployment.NettyProcessor#registerEventLoopBeans","started":"02:38:37.799","dependents":[295,292,339,290],"id":235,"thread":"build-29"},{"duration":0,"stepId":"io.quarkus.resteasy.reactive.server.deployment.ObservabilityProcessor#integrateObservability","started":"02:38:37.753","dependents":[314],"id":146,"thread":"build-2"},{"duration":0,"stepId":"io.quarkus.deployment.steps.BlockingOperationControlBuildStep#blockingOP","started":"02:38:37.766","dependents":[339],"id":171,"thread":"build-26"},{"duration":0,"stepId":"io.quarkus.deployment.pkg.steps.PackageTypeVerificationBuildStep#builtins","started":"02:38:37.737","dependents":[74],"id":29,"thread":"build-11"},{"duration":0,"stepId":"io.quarkus.swaggerui.deployment.SwaggerUiProcessor#feature","started":"02:38:37.735","dependents":[339],"id":22,"thread":"build-12"},{"duration":0,"stepId":"io.quarkus.resteasy.reactive.jackson.deployment.processor.ResteasyReactiveJacksonProcessor#feature","started":"02:38:37.750","dependents":[339],"id":139,"thread":"build-20"},{"duration":0,"stepId":"io.quarkus.resteasy.reactive.common.deployment.ResteasyReactiveCommonProcessor#scanForIOInterceptors","started":"02:38:37.785","dependents":[263],"id":214,"thread":"build-36"},{"duration":0,"stepId":"io.quarkus.deployment.steps.DevServicesConfigBuildStep#deprecated","started":"02:38:37.735","dependents":[33],"id":16,"thread":"build-7"},{"duration":0,"stepId":"org.kie.kogito.quarkus.common.deployment.KogitoInternalObjectMapperProvider#objectMapperImpl","started":"02:38:37.738","dependents":[338],"id":50,"thread":"build-19"},{"duration":0,"stepId":"io.quarkus.resteasy.reactive.server.deployment.ResteasyReactiveProcessor#registerCustomExceptionMappers","started":"02:38:37.749","dependents":[262],"id":138,"thread":"build-27"},{"duration":0,"stepId":"io.quarkus.deployment.steps.ReflectionDiagnosticProcessor#writeReflectionData","started":"02:38:39.290","dependents":[],"id":338,"thread":"build-25"},{"duration":0,"stepId":"io.quarkus.resteasy.reactive.server.deployment.ResteasyReactiveDevModeProcessor#setupExceptionMapper","started":"02:38:37.738","dependents":[262,339],"id":58,"thread":"build-18"}],"started":"2023-04-18T02:38:37.731","buildTarget":"MR-weather-advice-1.0.0-SNAPSHOT"}